{
  "timestamp": "2025-10-07T05:43:43.738151",
  "intelligence_score": 1.0,
  "emergence_detected": true,
  "code_history": [
    {
      "code": "self.intelligence_score += 0.01",
      "timestamp": "2025-10-07T05:36:34.891562",
      "success": true
    },
    {
      "code": "self.intelligence_score += 0.01",
      "timestamp": "2025-10-07T05:36:34.891836",
      "success": false,
      "error": "Extra data: line 14 column 2 (char 365)"
    },
    {
      "code": "self.intelligence_score += 0.01",
      "timestamp": "2025-10-07T05:36:35.893342",
      "success": true
    },
    {
      "code": "self.intelligence_score += 0.01",
      "timestamp": "2025-10-07T05:36:36.003543",
      "success": false,
      "error": "Extra data: line 14 column 2 (char 365)"
    },
    {
      "code": "logger.info('Auto-modifica\u00e7\u00e3o executada')",
      "timestamp": "2025-10-07T05:39:26.662275",
      "success": true
    },
    {
      "code": "logger.info('Auto-modifica\u00e7\u00e3o executada')",
      "timestamp": "2025-10-07T05:39:26.662540",
      "success": false,
      "error": "Extra data: line 14 column 2 (char 365)"
    },
    {
      "code": "self.emergence_detected = self.intelligence_score > 0.8",
      "timestamp": "2025-10-07T05:39:27.663870",
      "success": true
    },
    {
      "code": "self.emergence_detected = self.intelligence_score > 0.8",
      "timestamp": "2025-10-07T05:39:27.664163",
      "success": false,
      "error": "Extra data: line 14 column 2 (char 365)"
    },
    {
      "code": "print(f'Ciclo: {self.code_history.__len__()}')",
      "timestamp": "2025-10-07T05:39:28.664704",
      "success": true
    },
    {
      "code": "print(f'Ciclo: {self.code_history.__len__()}')",
      "timestamp": "2025-10-07T05:39:28.665033",
      "success": false,
      "error": "Extra data: line 14 column 2 (char 365)"
    },
    {
      "code": "self.intelligence_score += 0.01",
      "timestamp": "2025-10-07T05:39:29.667078",
      "success": true
    },
    {
      "code": "self.intelligence_score += 0.01",
      "timestamp": "2025-10-07T05:39:29.667794",
      "success": false,
      "error": "Extra data: line 14 column 2 (char 365)"
    },
    {
      "code": "import random; self.intelligence_score += random.uniform(0, 0.05)",
      "timestamp": "2025-10-07T05:39:30.669115",
      "success": true
    },
    {
      "code": "import random; self.intelligence_score += random.uniform(0, 0.05)",
      "timestamp": "2025-10-07T05:39:30.687380",
      "success": false,
      "error": "Extra data: line 14 column 2 (char 365)"
    },
    {
      "code": "if self.intelligence_score > 0.5: self.emergence_detected = True",
      "timestamp": "2025-10-07T05:39:31.688208",
      "success": true
    },
    {
      "code": "if self.intelligence_score > 0.5: self.emergence_detected = True",
      "timestamp": "2025-10-07T05:39:32.001446",
      "success": false,
      "error": "Extra data: line 14 column 2 (char 365)"
    },
    {
      "code": "self.emergence_detected = True",
      "timestamp": "2025-10-07T05:39:33.001998",
      "success": true
    },
    {
      "code": "self.emergence_detected = True",
      "timestamp": "2025-10-07T05:39:33.002261",
      "success": false,
      "error": "Extra data: line 14 column 2 (char 365)"
    },
    {
      "code": "logger.info('Auto-modifica\u00e7\u00e3o executada')",
      "timestamp": "2025-10-07T05:39:34.003695",
      "success": true
    },
    {
      "code": "logger.info('Auto-modifica\u00e7\u00e3o executada')",
      "timestamp": "2025-10-07T05:39:34.003920",
      "success": false,
      "error": "Extra data: line 14 column 2 (char 365)"
    },
    {
      "code": "logger.info('Auto-modifica\u00e7\u00e3o executada')",
      "timestamp": "2025-10-07T05:39:35.005259",
      "success": true
    },
    {
      "code": "logger.info('Auto-modifica\u00e7\u00e3o executada')",
      "timestamp": "2025-10-07T05:39:35.005450",
      "success": false,
      "error": "Extra data: line 14 column 2 (char 365)"
    },
    {
      "code": "success_rate = sum(1 for c in self.code_history if c.get('success')) / max(1, len(self.code_history))",
      "timestamp": "2025-10-07T05:39:36.018668",
      "success": true
    },
    {
      "code": "success_rate = sum(1 for c in self.code_history if c.get('success')) / max(1, len(self.code_history))",
      "timestamp": "2025-10-07T05:39:36.989889",
      "success": false,
      "error": "Extra data: line 14 column 2 (char 365)"
    },
    {
      "code": "import random; self.intelligence_score += random.uniform(0, 0.05)",
      "timestamp": "2025-10-07T05:39:38.632547",
      "success": true
    },
    {
      "code": "import random; self.intelligence_score += random.uniform(0, 0.05)",
      "timestamp": "2025-10-07T05:39:38.632812",
      "success": false,
      "error": "Extra data: line 14 column 2 (char 365)"
    },
    {
      "code": "if len(self.code_history) > 100: self.intelligence_score += 0.1",
      "timestamp": "2025-10-07T05:39:39.634101",
      "success": true
    },
    {
      "code": "if len(self.code_history) > 100: self.intelligence_score += 0.1",
      "timestamp": "2025-10-07T05:39:39.634405",
      "success": false,
      "error": "Extra data: line 14 column 2 (char 365)"
    },
    {
      "code": "import random; self.intelligence_score += random.uniform(0, 0.05)",
      "timestamp": "2025-10-07T05:39:40.635105",
      "success": true
    },
    {
      "code": "import random; self.intelligence_score += random.uniform(0, 0.05)",
      "timestamp": "2025-10-07T05:39:40.635343",
      "success": false,
      "error": "Extra data: line 14 column 2 (char 365)"
    },
    {
      "code": "logger.info('Auto-modifica\u00e7\u00e3o executada')",
      "timestamp": "2025-10-07T05:39:41.639504",
      "success": true
    },
    {
      "code": "logger.info('Auto-modifica\u00e7\u00e3o executada')",
      "timestamp": "2025-10-07T05:39:41.639727",
      "success": false,
      "error": "Extra data: line 14 column 2 (char 365)"
    },
    {
      "code": "success_rate = sum(1 for c in self.code_history if c.get('success')) / max(1, len(self.code_history))",
      "timestamp": "2025-10-07T05:39:42.652583",
      "success": true
    },
    {
      "code": "success_rate = sum(1 for c in self.code_history if c.get('success')) / max(1, len(self.code_history))",
      "timestamp": "2025-10-07T05:39:42.977822",
      "success": false,
      "error": "Extra data: line 14 column 2 (char 365)"
    },
    {
      "code": "print(f'Intelig\u00eancia: {self.intelligence_score}')",
      "timestamp": "2025-10-07T05:39:43.980603",
      "success": true
    },
    {
      "code": "print(f'Intelig\u00eancia: {self.intelligence_score}')",
      "timestamp": "2025-10-07T05:39:43.980849",
      "success": false,
      "error": "Extra data: line 14 column 2 (char 365)"
    },
    {
      "code": "if self.intelligence_score > 0.5: self.emergence_detected = True",
      "timestamp": "2025-10-07T05:39:44.982022",
      "success": true
    },
    {
      "code": "if self.intelligence_score > 0.5: self.emergence_detected = True",
      "timestamp": "2025-10-07T05:39:44.982229",
      "success": false,
      "error": "Extra data: line 14 column 2 (char 365)"
    },
    {
      "code": "import random; self.intelligence_score += random.uniform(0, 0.05)",
      "timestamp": "2025-10-07T05:39:45.987722",
      "success": true
    },
    {
      "code": "import random; self.intelligence_score += random.uniform(0, 0.05)",
      "timestamp": "2025-10-07T05:39:45.991355",
      "success": false,
      "error": "Extra data: line 14 column 2 (char 365)"
    },
    {
      "code": "if self.intelligence_score > 0.5: self.emergence_detected = True",
      "timestamp": "2025-10-07T05:39:46.994813",
      "success": true
    },
    {
      "code": "if self.intelligence_score > 0.5: self.emergence_detected = True",
      "timestamp": "2025-10-07T05:39:47.975028",
      "success": false,
      "error": "Extra data: line 14 column 2 (char 365)"
    },
    {
      "code": "print(f'Ciclo: {self.code_history.__len__()}')",
      "timestamp": "2025-10-07T05:39:49.016332",
      "success": true
    },
    {
      "code": "print(f'Ciclo: {self.code_history.__len__()}')",
      "timestamp": "2025-10-07T05:39:49.016525",
      "success": false,
      "error": "Extra data: line 14 column 2 (char 365)"
    },
    {
      "code": "print(f'Intelig\u00eancia: {self.intelligence_score}')",
      "timestamp": "2025-10-07T05:39:50.017410",
      "success": true
    },
    {
      "code": "print(f'Intelig\u00eancia: {self.intelligence_score}')",
      "timestamp": "2025-10-07T05:39:50.017660",
      "success": false,
      "error": "Extra data: line 14 column 2 (char 365)"
    },
    {
      "code": "print(f'Intelig\u00eancia: {self.intelligence_score}')",
      "timestamp": "2025-10-07T05:39:51.018873",
      "success": true
    },
    {
      "code": "print(f'Intelig\u00eancia: {self.intelligence_score}')",
      "timestamp": "2025-10-07T05:39:51.019073",
      "success": false,
      "error": "Extra data: line 14 column 2 (char 365)"
    },
    {
      "code": "print(f'Ciclo: {self.code_history.__len__()}')",
      "timestamp": "2025-10-07T05:39:52.020448",
      "success": true
    },
    {
      "code": "print(f'Ciclo: {self.code_history.__len__()}')",
      "timestamp": "2025-10-07T05:39:52.020684",
      "success": false,
      "error": "Extra data: line 14 column 2 (char 365)"
    },
    {
      "code": "import random; self.intelligence_score += random.uniform(0, 0.05)",
      "timestamp": "2025-10-07T05:39:53.034063",
      "success": true
    },
    {
      "code": "import random; self.intelligence_score += random.uniform(0, 0.05)",
      "timestamp": "2025-10-07T05:39:53.034334",
      "success": false,
      "error": "Extra data: line 14 column 2 (char 365)"
    },
    {
      "code": "print(f'Ciclo: {self.code_history.__len__()}')",
      "timestamp": "2025-10-07T05:43:15.613809",
      "success": true
    },
    {
      "code": "print(f'Ciclo: {self.code_history.__len__()}')",
      "timestamp": "2025-10-07T05:43:18.579418",
      "success": false,
      "error": "Extra data: line 14 column 2 (char 365)"
    },
    {
      "code": "if len(self.code_history) > 100: self.intelligence_score += 0.1",
      "timestamp": "2025-10-07T05:43:19.579957",
      "success": true
    },
    {
      "code": "if len(self.code_history) > 100: self.intelligence_score += 0.1",
      "timestamp": "2025-10-07T05:43:19.580222",
      "success": false,
      "error": "Extra data: line 14 column 2 (char 365)"
    },
    {
      "code": "print(f'Taxa de sucesso: {success_rate:.2f}')",
      "timestamp": "2025-10-07T05:43:20.594089",
      "success": true
    },
    {
      "code": "print(f'Taxa de sucesso: {success_rate:.2f}')",
      "timestamp": "2025-10-07T05:43:20.594348",
      "success": false,
      "error": "Extra data: line 14 column 2 (char 365)"
    },
    {
      "code": "print(f'Intelig\u00eancia: {self.intelligence_score}')",
      "timestamp": "2025-10-07T05:43:21.604191",
      "success": true
    },
    {
      "code": "print(f'Intelig\u00eancia: {self.intelligence_score}')",
      "timestamp": "2025-10-07T05:43:21.628699",
      "success": false,
      "error": "Extra data: line 14 column 2 (char 365)"
    },
    {
      "code": "self.intelligence_score += 0.01",
      "timestamp": "2025-10-07T05:43:22.631249",
      "success": true
    },
    {
      "code": "self.intelligence_score += 0.01",
      "timestamp": "2025-10-07T05:43:22.749287",
      "success": false,
      "error": "Extra data: line 14 column 2 (char 365)"
    },
    {
      "code": "import random; self.intelligence_score += random.uniform(0, 0.05)",
      "timestamp": "2025-10-07T05:43:23.750280",
      "success": true
    },
    {
      "code": "import random; self.intelligence_score += random.uniform(0, 0.05)",
      "timestamp": "2025-10-07T05:43:23.750469",
      "success": false,
      "error": "Extra data: line 14 column 2 (char 365)"
    },
    {
      "code": "print(f'Intelig\u00eancia: {self.intelligence_score}')",
      "timestamp": "2025-10-07T05:43:24.751747",
      "success": true
    },
    {
      "code": "print(f'Intelig\u00eancia: {self.intelligence_score}')",
      "timestamp": "2025-10-07T05:43:24.751966",
      "success": false,
      "error": "Extra data: line 14 column 2 (char 365)"
    },
    {
      "code": "self.emergence_detected = self.intelligence_score > 0.8",
      "timestamp": "2025-10-07T05:43:25.753290",
      "success": true
    },
    {
      "code": "self.emergence_detected = self.intelligence_score > 0.8",
      "timestamp": "2025-10-07T05:43:25.753499",
      "success": false,
      "error": "Extra data: line 14 column 2 (char 365)"
    },
    {
      "code": "self.emergence_detected = self.intelligence_score > 0.8",
      "timestamp": "2025-10-07T05:43:26.754351",
      "success": true
    },
    {
      "code": "self.emergence_detected = self.intelligence_score > 0.8",
      "timestamp": "2025-10-07T05:43:27.603695",
      "success": false,
      "error": "Extra data: line 14 column 2 (char 365)"
    },
    {
      "code": "self.emergence_detected = True",
      "timestamp": "2025-10-07T05:43:28.605040",
      "success": true
    },
    {
      "code": "self.emergence_detected = True",
      "timestamp": "2025-10-07T05:43:28.979202",
      "success": false,
      "error": "Extra data: line 14 column 2 (char 365)"
    },
    {
      "code": "import random; self.intelligence_score += random.uniform(0, 0.05)",
      "timestamp": "2025-10-07T05:43:30.032732",
      "success": true
    },
    {
      "code": "import random; self.intelligence_score += random.uniform(0, 0.05)",
      "timestamp": "2025-10-07T05:43:30.033025",
      "success": false,
      "error": "Extra data: line 14 column 2 (char 365)"
    },
    {
      "code": "import random; self.intelligence_score += random.uniform(0, 0.05)",
      "timestamp": "2025-10-07T05:43:31.034122",
      "success": true
    },
    {
      "code": "import random; self.intelligence_score += random.uniform(0, 0.05)",
      "timestamp": "2025-10-07T05:43:31.034321",
      "success": false,
      "error": "Extra data: line 14 column 2 (char 365)"
    },
    {
      "code": "print(f'Ciclo: {self.code_history.__len__()}')",
      "timestamp": "2025-10-07T05:43:32.053677",
      "success": true
    },
    {
      "code": "print(f'Ciclo: {self.code_history.__len__()}')",
      "timestamp": "2025-10-07T05:43:32.068835",
      "success": false,
      "error": "Extra data: line 14 column 2 (char 365)"
    },
    {
      "code": "self.intelligence_score += 0.01",
      "timestamp": "2025-10-07T05:43:33.070132",
      "success": true
    },
    {
      "code": "self.intelligence_score += 0.01",
      "timestamp": "2025-10-07T05:43:33.095199",
      "success": false,
      "error": "Extra data: line 14 column 2 (char 365)"
    },
    {
      "code": "print(f'Intelig\u00eancia: {self.intelligence_score}')",
      "timestamp": "2025-10-07T05:43:34.096637",
      "success": true
    },
    {
      "code": "print(f'Intelig\u00eancia: {self.intelligence_score}')",
      "timestamp": "2025-10-07T05:43:34.412353",
      "success": false,
      "error": "Extra data: line 14 column 2 (char 365)"
    },
    {
      "code": "self.intelligence_score += 0.01",
      "timestamp": "2025-10-07T05:43:35.412911",
      "success": true
    },
    {
      "code": "self.intelligence_score += 0.01",
      "timestamp": "2025-10-07T05:43:35.413183",
      "success": false,
      "error": "Extra data: line 14 column 2 (char 365)"
    },
    {
      "code": "import random; self.intelligence_score += random.uniform(0, 0.05)",
      "timestamp": "2025-10-07T05:43:36.414029",
      "success": true
    },
    {
      "code": "import random; self.intelligence_score += random.uniform(0, 0.05)",
      "timestamp": "2025-10-07T05:43:36.414352",
      "success": false,
      "error": "Extra data: line 14 column 2 (char 365)"
    },
    {
      "code": "print(f'Ciclo: {self.code_history.__len__()}')",
      "timestamp": "2025-10-07T05:43:37.415622",
      "success": true
    },
    {
      "code": "print(f'Ciclo: {self.code_history.__len__()}')",
      "timestamp": "2025-10-07T05:43:37.610777",
      "success": false,
      "error": "Extra data: line 14 column 2 (char 365)"
    },
    {
      "code": "self.emergence_detected = True",
      "timestamp": "2025-10-07T05:43:38.612131",
      "success": true
    },
    {
      "code": "self.emergence_detected = True",
      "timestamp": "2025-10-07T05:43:38.612342",
      "success": false,
      "error": "Extra data: line 14 column 2 (char 365)"
    },
    {
      "code": "self.emergence_detected = True",
      "timestamp": "2025-10-07T05:43:39.618308",
      "success": true
    },
    {
      "code": "self.emergence_detected = True",
      "timestamp": "2025-10-07T05:43:39.618602",
      "success": false,
      "error": "Extra data: line 14 column 2 (char 365)"
    },
    {
      "code": "print(f'Taxa de sucesso: {success_rate:.2f}')",
      "timestamp": "2025-10-07T05:43:40.619987",
      "success": true
    },
    {
      "code": "print(f'Taxa de sucesso: {success_rate:.2f}')",
      "timestamp": "2025-10-07T05:43:40.620319",
      "success": false,
      "error": "Extra data: line 14 column 2 (char 365)"
    },
    {
      "code": "self.emergence_detected = True",
      "timestamp": "2025-10-07T05:43:41.620725",
      "success": true
    },
    {
      "code": "self.emergence_detected = True",
      "timestamp": "2025-10-07T05:43:41.621706",
      "success": false,
      "error": "Extra data: line 14 column 2 (char 365)"
    },
    {
      "code": "if len(self.code_history) > 100: self.intelligence_score += 0.1",
      "timestamp": "2025-10-07T05:43:42.622037",
      "success": true
    },
    {
      "code": "if len(self.code_history) > 100: self.intelligence_score += 0.1",
      "timestamp": "2025-10-07T05:43:42.622264",
      "success": false,
      "error": "Extra data: line 14 column 2 (char 365)"
    },
    {
      "code": "logger.info('Auto-modifica\u00e7\u00e3o executada')",
      "timestamp": "2025-10-07T05:43:43.623768",
      "success": true
    },
    {
      "code": "logger.info('Auto-modifica\u00e7\u00e3o executada')",
      "timestamp": "2025-10-07T05:43:43.624101",
      "success": false,
      "error": "Extra data: line 14 column 2 (char 365)"
    }
  ],
  "total_cycles": 16911
}