{
  "timestamp": "2025-10-07T02:21:05.196300",
  "intelligence_score": 1.0,
  "emergence_detected": true,
  "code_history": [
    {
      "code": "self.intelligence_score += 0.01",
      "timestamp": "2025-10-07T02:20:14.582008",
      "success": true
    },
    {
      "code": "self.intelligence_score += 0.01",
      "timestamp": "2025-10-07T02:20:14.582904",
      "success": false,
      "error": "Extra data: line 14 column 2 (char 365)"
    },
    {
      "code": "import random; self.intelligence_score += random.uniform(0, 0.05)",
      "timestamp": "2025-10-07T02:20:15.584284",
      "success": true
    },
    {
      "code": "import random; self.intelligence_score += random.uniform(0, 0.05)",
      "timestamp": "2025-10-07T02:20:15.584562",
      "success": false,
      "error": "Extra data: line 14 column 2 (char 365)"
    },
    {
      "code": "print(f'Intelig\u00eancia: {self.intelligence_score}')",
      "timestamp": "2025-10-07T02:20:16.585897",
      "success": true
    },
    {
      "code": "print(f'Intelig\u00eancia: {self.intelligence_score}')",
      "timestamp": "2025-10-07T02:20:16.617353",
      "success": false,
      "error": "Extra data: line 14 column 2 (char 365)"
    },
    {
      "code": "print(f'Intelig\u00eancia: {self.intelligence_score}')",
      "timestamp": "2025-10-07T02:20:17.618159",
      "success": true
    },
    {
      "code": "print(f'Intelig\u00eancia: {self.intelligence_score}')",
      "timestamp": "2025-10-07T02:20:17.618460",
      "success": false,
      "error": "Extra data: line 14 column 2 (char 365)"
    },
    {
      "code": "success_rate = sum(1 for c in self.code_history if c.get('success')) / max(1, len(self.code_history))",
      "timestamp": "2025-10-07T02:20:18.620999",
      "success": true
    },
    {
      "code": "success_rate = sum(1 for c in self.code_history if c.get('success')) / max(1, len(self.code_history))",
      "timestamp": "2025-10-07T02:20:18.621304",
      "success": false,
      "error": "Extra data: line 14 column 2 (char 365)"
    },
    {
      "code": "self.intelligence_score += 0.01",
      "timestamp": "2025-10-07T02:20:19.622022",
      "success": true
    },
    {
      "code": "self.intelligence_score += 0.01",
      "timestamp": "2025-10-07T02:20:19.622304",
      "success": false,
      "error": "Extra data: line 14 column 2 (char 365)"
    },
    {
      "code": "print(f'Taxa de sucesso: {success_rate:.2f}')",
      "timestamp": "2025-10-07T02:20:20.623639",
      "success": true
    },
    {
      "code": "print(f'Taxa de sucesso: {success_rate:.2f}')",
      "timestamp": "2025-10-07T02:20:20.623938",
      "success": false,
      "error": "Extra data: line 14 column 2 (char 365)"
    },
    {
      "code": "print(f'Intelig\u00eancia: {self.intelligence_score}')",
      "timestamp": "2025-10-07T02:20:21.628128",
      "success": true
    },
    {
      "code": "print(f'Intelig\u00eancia: {self.intelligence_score}')",
      "timestamp": "2025-10-07T02:20:21.639297",
      "success": false,
      "error": "Extra data: line 14 column 2 (char 365)"
    },
    {
      "code": "success_rate = sum(1 for c in self.code_history if c.get('success')) / max(1, len(self.code_history))",
      "timestamp": "2025-10-07T02:20:22.731918",
      "success": true
    },
    {
      "code": "success_rate = sum(1 for c in self.code_history if c.get('success')) / max(1, len(self.code_history))",
      "timestamp": "2025-10-07T02:20:22.732170",
      "success": false,
      "error": "Extra data: line 14 column 2 (char 365)"
    },
    {
      "code": "success_rate = sum(1 for c in self.code_history if c.get('success')) / max(1, len(self.code_history))",
      "timestamp": "2025-10-07T02:20:23.736877",
      "success": true
    },
    {
      "code": "success_rate = sum(1 for c in self.code_history if c.get('success')) / max(1, len(self.code_history))",
      "timestamp": "2025-10-07T02:20:23.737156",
      "success": false,
      "error": "Extra data: line 14 column 2 (char 365)"
    },
    {
      "code": "import random; self.intelligence_score += random.uniform(0, 0.05)",
      "timestamp": "2025-10-07T02:20:24.753864",
      "success": true
    },
    {
      "code": "import random; self.intelligence_score += random.uniform(0, 0.05)",
      "timestamp": "2025-10-07T02:20:24.754139",
      "success": false,
      "error": "Extra data: line 14 column 2 (char 365)"
    },
    {
      "code": "print(f'Taxa de sucesso: {success_rate:.2f}')",
      "timestamp": "2025-10-07T02:20:25.755425",
      "success": true
    },
    {
      "code": "print(f'Taxa de sucesso: {success_rate:.2f}')",
      "timestamp": "2025-10-07T02:20:25.755646",
      "success": false,
      "error": "Extra data: line 14 column 2 (char 365)"
    },
    {
      "code": "if len(self.code_history) > 100: self.intelligence_score += 0.1",
      "timestamp": "2025-10-07T02:20:26.756907",
      "success": true
    },
    {
      "code": "if len(self.code_history) > 100: self.intelligence_score += 0.1",
      "timestamp": "2025-10-07T02:20:26.761209",
      "success": false,
      "error": "Extra data: line 14 column 2 (char 365)"
    },
    {
      "code": "print(f'Ciclo: {self.code_history.__len__()}')",
      "timestamp": "2025-10-07T02:20:27.762067",
      "success": true
    },
    {
      "code": "print(f'Ciclo: {self.code_history.__len__()}')",
      "timestamp": "2025-10-07T02:20:27.762296",
      "success": false,
      "error": "Extra data: line 14 column 2 (char 365)"
    },
    {
      "code": "self.intelligence_score += 0.01",
      "timestamp": "2025-10-07T02:20:28.764379",
      "success": true
    },
    {
      "code": "self.intelligence_score += 0.01",
      "timestamp": "2025-10-07T02:20:28.764562",
      "success": false,
      "error": "Extra data: line 14 column 2 (char 365)"
    },
    {
      "code": "print(f'Taxa de sucesso: {success_rate:.2f}')",
      "timestamp": "2025-10-07T02:20:29.765211",
      "success": true
    },
    {
      "code": "print(f'Taxa de sucesso: {success_rate:.2f}')",
      "timestamp": "2025-10-07T02:20:29.765460",
      "success": false,
      "error": "Extra data: line 14 column 2 (char 365)"
    },
    {
      "code": "import random; self.intelligence_score += random.uniform(0, 0.05)",
      "timestamp": "2025-10-07T02:20:30.766042",
      "success": true
    },
    {
      "code": "import random; self.intelligence_score += random.uniform(0, 0.05)",
      "timestamp": "2025-10-07T02:20:30.766289",
      "success": false,
      "error": "Extra data: line 14 column 2 (char 365)"
    },
    {
      "code": "print(f'Intelig\u00eancia: {self.intelligence_score}')",
      "timestamp": "2025-10-07T02:20:31.767587",
      "success": true
    },
    {
      "code": "print(f'Intelig\u00eancia: {self.intelligence_score}')",
      "timestamp": "2025-10-07T02:20:31.961301",
      "success": false,
      "error": "Extra data: line 14 column 2 (char 365)"
    },
    {
      "code": "logger.info('Auto-modifica\u00e7\u00e3o executada')",
      "timestamp": "2025-10-07T02:20:32.962125",
      "success": true
    },
    {
      "code": "logger.info('Auto-modifica\u00e7\u00e3o executada')",
      "timestamp": "2025-10-07T02:20:32.962295",
      "success": false,
      "error": "Extra data: line 14 column 2 (char 365)"
    },
    {
      "code": "self.emergence_detected = True",
      "timestamp": "2025-10-07T02:20:33.969965",
      "success": true
    },
    {
      "code": "self.emergence_detected = True",
      "timestamp": "2025-10-07T02:20:33.987136",
      "success": false,
      "error": "Extra data: line 14 column 2 (char 365)"
    },
    {
      "code": "print(f'Taxa de sucesso: {success_rate:.2f}')",
      "timestamp": "2025-10-07T02:20:34.988599",
      "success": true
    },
    {
      "code": "print(f'Taxa de sucesso: {success_rate:.2f}')",
      "timestamp": "2025-10-07T02:20:34.988898",
      "success": false,
      "error": "Extra data: line 14 column 2 (char 365)"
    },
    {
      "code": "self.emergence_detected = True",
      "timestamp": "2025-10-07T02:20:35.990020",
      "success": true
    },
    {
      "code": "self.emergence_detected = True",
      "timestamp": "2025-10-07T02:20:35.990300",
      "success": false,
      "error": "Extra data: line 14 column 2 (char 365)"
    },
    {
      "code": "logger.info('Auto-modifica\u00e7\u00e3o executada')",
      "timestamp": "2025-10-07T02:20:36.991784",
      "success": true
    },
    {
      "code": "logger.info('Auto-modifica\u00e7\u00e3o executada')",
      "timestamp": "2025-10-07T02:20:36.991984",
      "success": false,
      "error": "Extra data: line 14 column 2 (char 365)"
    },
    {
      "code": "self.emergence_detected = True",
      "timestamp": "2025-10-07T02:20:37.993228",
      "success": true
    },
    {
      "code": "self.emergence_detected = True",
      "timestamp": "2025-10-07T02:20:37.993479",
      "success": false,
      "error": "Extra data: line 14 column 2 (char 365)"
    },
    {
      "code": "if self.intelligence_score > 0.5: self.emergence_detected = True",
      "timestamp": "2025-10-07T02:20:38.997925",
      "success": true
    },
    {
      "code": "if self.intelligence_score > 0.5: self.emergence_detected = True",
      "timestamp": "2025-10-07T02:20:39.006404",
      "success": false,
      "error": "Extra data: line 14 column 2 (char 365)"
    },
    {
      "code": "print(f'Taxa de sucesso: {success_rate:.2f}')",
      "timestamp": "2025-10-07T02:20:40.007798",
      "success": true
    },
    {
      "code": "print(f'Taxa de sucesso: {success_rate:.2f}')",
      "timestamp": "2025-10-07T02:20:40.008058",
      "success": false,
      "error": "Extra data: line 14 column 2 (char 365)"
    },
    {
      "code": "import random; self.intelligence_score += random.uniform(0, 0.05)",
      "timestamp": "2025-10-07T02:20:41.009355",
      "success": true
    },
    {
      "code": "import random; self.intelligence_score += random.uniform(0, 0.05)",
      "timestamp": "2025-10-07T02:20:41.009626",
      "success": false,
      "error": "Extra data: line 14 column 2 (char 365)"
    },
    {
      "code": "print(f'Ciclo: {self.code_history.__len__()}')",
      "timestamp": "2025-10-07T02:20:42.011411",
      "success": true
    },
    {
      "code": "print(f'Ciclo: {self.code_history.__len__()}')",
      "timestamp": "2025-10-07T02:20:42.011637",
      "success": false,
      "error": "Extra data: line 14 column 2 (char 365)"
    },
    {
      "code": "success_rate = sum(1 for c in self.code_history if c.get('success')) / max(1, len(self.code_history))",
      "timestamp": "2025-10-07T02:20:43.014319",
      "success": true
    },
    {
      "code": "success_rate = sum(1 for c in self.code_history if c.get('success')) / max(1, len(self.code_history))",
      "timestamp": "2025-10-07T02:20:43.015682",
      "success": false,
      "error": "Extra data: line 14 column 2 (char 365)"
    },
    {
      "code": "print(f'Intelig\u00eancia: {self.intelligence_score}')",
      "timestamp": "2025-10-07T02:20:44.017195",
      "success": true
    },
    {
      "code": "print(f'Intelig\u00eancia: {self.intelligence_score}')",
      "timestamp": "2025-10-07T02:20:44.023740",
      "success": false,
      "error": "Extra data: line 14 column 2 (char 365)"
    },
    {
      "code": "if len(self.code_history) > 100: self.intelligence_score += 0.1",
      "timestamp": "2025-10-07T02:20:45.027390",
      "success": true
    },
    {
      "code": "if len(self.code_history) > 100: self.intelligence_score += 0.1",
      "timestamp": "2025-10-07T02:20:45.027642",
      "success": false,
      "error": "Extra data: line 14 column 2 (char 365)"
    },
    {
      "code": "if self.intelligence_score > 0.5: self.emergence_detected = True",
      "timestamp": "2025-10-07T02:20:46.028948",
      "success": true
    },
    {
      "code": "if self.intelligence_score > 0.5: self.emergence_detected = True",
      "timestamp": "2025-10-07T02:20:46.029254",
      "success": false,
      "error": "Extra data: line 14 column 2 (char 365)"
    },
    {
      "code": "success_rate = sum(1 for c in self.code_history if c.get('success')) / max(1, len(self.code_history))",
      "timestamp": "2025-10-07T02:20:47.061525",
      "success": true
    },
    {
      "code": "success_rate = sum(1 for c in self.code_history if c.get('success')) / max(1, len(self.code_history))",
      "timestamp": "2025-10-07T02:20:47.068058",
      "success": false,
      "error": "Extra data: line 14 column 2 (char 365)"
    },
    {
      "code": "print(f'Taxa de sucesso: {success_rate:.2f}')",
      "timestamp": "2025-10-07T02:20:48.074962",
      "success": true
    },
    {
      "code": "print(f'Taxa de sucesso: {success_rate:.2f}')",
      "timestamp": "2025-10-07T02:20:48.080403",
      "success": false,
      "error": "Extra data: line 14 column 2 (char 365)"
    },
    {
      "code": "success_rate = sum(1 for c in self.code_history if c.get('success')) / max(1, len(self.code_history))",
      "timestamp": "2025-10-07T02:20:49.100761",
      "success": true
    },
    {
      "code": "success_rate = sum(1 for c in self.code_history if c.get('success')) / max(1, len(self.code_history))",
      "timestamp": "2025-10-07T02:20:49.111222",
      "success": false,
      "error": "Extra data: line 14 column 2 (char 365)"
    },
    {
      "code": "print(f'Intelig\u00eancia: {self.intelligence_score}')",
      "timestamp": "2025-10-07T02:20:50.114277",
      "success": true
    },
    {
      "code": "print(f'Intelig\u00eancia: {self.intelligence_score}')",
      "timestamp": "2025-10-07T02:20:50.114468",
      "success": false,
      "error": "Extra data: line 14 column 2 (char 365)"
    },
    {
      "code": "print(f'Ciclo: {self.code_history.__len__()}')",
      "timestamp": "2025-10-07T02:20:51.130702",
      "success": true
    },
    {
      "code": "print(f'Ciclo: {self.code_history.__len__()}')",
      "timestamp": "2025-10-07T02:20:51.130904",
      "success": false,
      "error": "Extra data: line 14 column 2 (char 365)"
    },
    {
      "code": "success_rate = sum(1 for c in self.code_history if c.get('success')) / max(1, len(self.code_history))",
      "timestamp": "2025-10-07T02:20:52.133521",
      "success": true
    },
    {
      "code": "success_rate = sum(1 for c in self.code_history if c.get('success')) / max(1, len(self.code_history))",
      "timestamp": "2025-10-07T02:20:52.133828",
      "success": false,
      "error": "Extra data: line 14 column 2 (char 365)"
    },
    {
      "code": "self.emergence_detected = True",
      "timestamp": "2025-10-07T02:20:53.135124",
      "success": true
    },
    {
      "code": "self.emergence_detected = True",
      "timestamp": "2025-10-07T02:20:53.135383",
      "success": false,
      "error": "Extra data: line 14 column 2 (char 365)"
    },
    {
      "code": "print(f'Intelig\u00eancia: {self.intelligence_score}')",
      "timestamp": "2025-10-07T02:20:54.163924",
      "success": true
    },
    {
      "code": "print(f'Intelig\u00eancia: {self.intelligence_score}')",
      "timestamp": "2025-10-07T02:20:54.182053",
      "success": false,
      "error": "Extra data: line 14 column 2 (char 365)"
    },
    {
      "code": "self.emergence_detected = self.intelligence_score > 0.8",
      "timestamp": "2025-10-07T02:20:55.205551",
      "success": true
    },
    {
      "code": "self.emergence_detected = self.intelligence_score > 0.8",
      "timestamp": "2025-10-07T02:20:55.210473",
      "success": false,
      "error": "Extra data: line 14 column 2 (char 365)"
    },
    {
      "code": "print(f'Taxa de sucesso: {success_rate:.2f}')",
      "timestamp": "2025-10-07T02:20:56.220015",
      "success": true
    },
    {
      "code": "print(f'Taxa de sucesso: {success_rate:.2f}')",
      "timestamp": "2025-10-07T02:20:56.220262",
      "success": false,
      "error": "Extra data: line 14 column 2 (char 365)"
    },
    {
      "code": "if len(self.code_history) > 100: self.intelligence_score += 0.1",
      "timestamp": "2025-10-07T02:20:57.221671",
      "success": true
    },
    {
      "code": "if len(self.code_history) > 100: self.intelligence_score += 0.1",
      "timestamp": "2025-10-07T02:20:57.222010",
      "success": false,
      "error": "Extra data: line 14 column 2 (char 365)"
    },
    {
      "code": "self.emergence_detected = self.intelligence_score > 0.8",
      "timestamp": "2025-10-07T02:20:58.226905",
      "success": true
    },
    {
      "code": "self.emergence_detected = self.intelligence_score > 0.8",
      "timestamp": "2025-10-07T02:20:58.230871",
      "success": false,
      "error": "Extra data: line 14 column 2 (char 365)"
    },
    {
      "code": "success_rate = sum(1 for c in self.code_history if c.get('success')) / max(1, len(self.code_history))",
      "timestamp": "2025-10-07T02:20:59.239174",
      "success": true
    },
    {
      "code": "success_rate = sum(1 for c in self.code_history if c.get('success')) / max(1, len(self.code_history))",
      "timestamp": "2025-10-07T02:20:59.239422",
      "success": false,
      "error": "Extra data: line 14 column 2 (char 365)"
    },
    {
      "code": "print(f'Taxa de sucesso: {success_rate:.2f}')",
      "timestamp": "2025-10-07T02:21:00.241584",
      "success": true
    },
    {
      "code": "print(f'Taxa de sucesso: {success_rate:.2f}')",
      "timestamp": "2025-10-07T02:21:00.241962",
      "success": false,
      "error": "Extra data: line 14 column 2 (char 365)"
    },
    {
      "code": "success_rate = sum(1 for c in self.code_history if c.get('success')) / max(1, len(self.code_history))",
      "timestamp": "2025-10-07T02:21:01.244589",
      "success": true
    },
    {
      "code": "success_rate = sum(1 for c in self.code_history if c.get('success')) / max(1, len(self.code_history))",
      "timestamp": "2025-10-07T02:21:01.245970",
      "success": false,
      "error": "Extra data: line 14 column 2 (char 365)"
    },
    {
      "code": "print(f'Taxa de sucesso: {success_rate:.2f}')",
      "timestamp": "2025-10-07T02:21:02.247309",
      "success": true
    },
    {
      "code": "print(f'Taxa de sucesso: {success_rate:.2f}')",
      "timestamp": "2025-10-07T02:21:02.247577",
      "success": false,
      "error": "Extra data: line 14 column 2 (char 365)"
    },
    {
      "code": "if self.intelligence_score > 0.5: self.emergence_detected = True",
      "timestamp": "2025-10-07T02:21:03.248857",
      "success": true
    },
    {
      "code": "if self.intelligence_score > 0.5: self.emergence_detected = True",
      "timestamp": "2025-10-07T02:21:03.249119",
      "success": false,
      "error": "Extra data: line 14 column 2 (char 365)"
    },
    {
      "code": "if self.intelligence_score > 0.5: self.emergence_detected = True",
      "timestamp": "2025-10-07T02:21:04.258026",
      "success": true
    },
    {
      "code": "if self.intelligence_score > 0.5: self.emergence_detected = True",
      "timestamp": "2025-10-07T02:21:04.280373",
      "success": false,
      "error": "Extra data: line 14 column 2 (char 365)"
    }
  ],
  "total_cycles": 2479
}